setup.py
mayank_dist/Binomialdistribution.py
mayank_dist/Gaussiandistribution.py
mayank_dist/Generaldistribution.py
mayank_dist/__init__.py
mayank_dist.egg-info/PKG-INFO
mayank_dist.egg-info/SOURCES.txt
mayank_dist.egg-info/dependency_links.txt
mayank_dist.egg-info/not-zip-safe
mayank_dist.egg-info/top_level.txt